xdf4mne/__init__.py
xdf4mne/xdf.py
xdf4mne-0.0.4.dist-info/METADATA
xdf4mne-0.0.4.dist-info/WHEEL
xdf4mne-0.0.4.dist-info/entry_points.txt
xdf4mne-0.0.4.dist-info/top_level.txt
xdf4mne-0.0.4.dist-info/RECORD
