Metadata-Version: 2.1
Name: xdf4mne
Version: 0.0.4
Summary: Load XDF files into MNE
Home-page: UNKNOWN
License: CC copyleft
Keywords: xdf,mne
Platform: UNKNOWN
Classifier: Framework :: Django
Classifier: License :: OSI Approved :: BSD License
Classifier: Programming Language :: Python :: 3
Classifier: Programming Language :: Python :: 3.9
